README.md
pyproject.toml
setup.py
MeshFT.egg-info/PKG-INFO
MeshFT.egg-info/SOURCES.txt
MeshFT.egg-info/dependency_links.txt
MeshFT.egg-info/requires.txt
MeshFT.egg-info/top_level.txt
meshft/__init__.py
meshft/cuda_class.py
meshft/fourier.py