Metadata-Version: 2.1
Name: MeshFT
Version: 1.1.0
Summary: MeshFT implementation
Home-page: https://github.com/sacha-ichbiah/meshFT
Author: Sacha Ichbiah
Author-email: sacha.ichbiah@polytechnique.org
License: BSD
Classifier: Development Status :: 3 - Alpha
Classifier: Intended Audience :: Developers
Classifier: License :: OSI Approved :: BSD License
Classifier: Operating System :: OS Independent
Classifier: Programming Language :: Python
Classifier: Programming Language :: Python :: 3
Classifier: Programming Language :: Python :: 3.8
Classifier: Programming Language :: Python :: 3.9
Classifier: Programming Language :: Python :: 3.10
